README.md
README.rst
setup.py
jsonconfigreader/__init__.py
jsonconfigreader/json_config_reader.py
jsonconfigreader.egg-info/PKG-INFO
jsonconfigreader.egg-info/SOURCES.txt
jsonconfigreader.egg-info/dependency_links.txt
jsonconfigreader.egg-info/top_level.txt