Metadata-Version: 1.1
Name: jsonconfigreader
Version: 1.3.0
Summary: Python JSON configuration reader and parser
Home-page: https://github.com/AndreySurzhan/jsonconfigreader
Author: Andrei Surzhan
Author-email: surzhan.a.y@gmail.com
License: UNKNOWN
Platform: UNKNOWN
Classifier: Topic :: Utilities
Classifier: Intended Audience :: Developers
Classifier: Intended Audience :: Other Audience
Classifier: Operating System :: Microsoft :: Windows :: Windows 10
Classifier: Operating System :: MacOS
Classifier: Operating System :: Unix
Classifier: Programming Language :: Python
